MANIFEST.in
README.rst
setup.py
docs/HISTORY.txt
opengever/__init__.py
opengever.ogds.models.egg-info/PKG-INFO
opengever.ogds.models.egg-info/SOURCES.txt
opengever.ogds.models.egg-info/dependency_links.txt
opengever.ogds.models.egg-info/entry_points.txt
opengever.ogds.models.egg-info/namespace_packages.txt
opengever.ogds.models.egg-info/not-zip-safe
opengever.ogds.models.egg-info/requires.txt
opengever.ogds.models.egg-info/top_level.txt
opengever/ogds/__init__.py
opengever/ogds/models/__init__.py
opengever/ogds/models/admin_unit.py
opengever/ogds/models/declarative.py
opengever/ogds/models/exceptions.py
opengever/ogds/models/group.py
opengever/ogds/models/inbox.py
opengever/ogds/models/org_unit.py
opengever/ogds/models/query.py
opengever/ogds/models/service.py
opengever/ogds/models/team.py
opengever/ogds/models/testing.py
opengever/ogds/models/types.py
opengever/ogds/models/user.py
opengever/ogds/models/utils.py
opengever/ogds/models/tests/__init__.py
opengever/ogds/models/tests/base.py
opengever/ogds/models/tests/builders.py
opengever/ogds/models/tests/test_admin_unit.py
opengever/ogds/models/tests/test_group.py
opengever/ogds/models/tests/test_inbox.py
opengever/ogds/models/tests/test_org_unit.py
opengever/ogds/models/tests/test_query.py
opengever/ogds/models/tests/test_service.py
opengever/ogds/models/tests/test_team.py
opengever/ogds/models/tests/test_user.py