Metadata-Version: 1.1
Name: opengever.ogds.models
Version: 2.7.2
Summary: Models for OpenGever directory service (Maintainer 4teamwork AG)
Home-page: https://github.com/4teamwork/opengever.ogds.models
Author: 4teamwork AG
Author-email: mailto:info@4teamwork.ch
License: GPL2
Keywords: opengever ogds models
Platform: UNKNOWN
Classifier: Programming Language :: Python
Classifier: Topic :: Software Development :: Libraries :: Python Modules
